rtp_feedback_tool/__init__.py
rtp_feedback_tool/tool.py
rtp_feedback_tool-0.0.3.dist-info/LICENSE
rtp_feedback_tool-0.0.3.dist-info/METADATA
rtp_feedback_tool-0.0.3.dist-info/WHEEL
rtp_feedback_tool-0.0.3.dist-info/top_level.txt
rtp_feedback_tool-0.0.3.dist-info/RECORD
