Metadata-Version: 2.1
Name: rtp-feedback-tool
Version: 0.0.3
Summary: Robot Tasking Platform(RTP,机器人任务下发与状态同步平台)的数据反馈工具,在RTP下发的应用容器中使用
Author-email: HuaJuan Zhang <zhj630985214@gmail.com>
Project-URL: Homepage, https://gitee.com/zhj6848/robot-tasking-platform/tree/main/rtp-feedback-tool
Project-URL: Bug Tracker, https://gitee.com/zhj6848/robot-tasking-platform/issues
Classifier: Programming Language :: Python :: 3
Classifier: License :: OSI Approved :: MIT License
Classifier: Operating System :: OS Independent
Requires-Python: >=3.6
License-File: LICENSE
Requires-Dist: numpy (>=1.15.0)
Requires-Dist: paho-mqtt (>=1.5.0)
Requires-Dist: Pillow (>=5.0.0)
